chrome_extension_info/__init__.py
chrome_extension_info/client.py
chrome_extension_info/exceptions.py
chrome_extension_info/models.py
chrome_extension_info-0.2.1.dist-info/licenses/LICENSE
tests/__init__.py
tests/test_client.py
tests/test_models.py
chrome_extension_info-0.2.1.dist-info/METADATA
chrome_extension_info-0.2.1.dist-info/WHEEL
chrome_extension_info-0.2.1.dist-info/top_level.txt
chrome_extension_info-0.2.1.dist-info/RECORD
